{
  "ts": "2025-12-18T11:24:28.058Z",
  "packs": [
    "pack.ayurveda.js",
    "pack.brand-look.js",
    "pack.face-sothys.js",
    "pack.hamam.js",
    "pack.kids.js",
    "pack.kids.premium.js",
    "pack.recovery.js",
    "pack.seasonal-detox.js",
    "pack.signature-family-teen.js",
    "pack.signature.js"
  ],
  "totalPrompts": 53,
  "errors": [],
  "warnings": [],
  "status": "PASS",
  "metrics": {
    "version": "mega-metrics.v1",
    "generatedAt": "2025-12-18T11:24:28.039Z",
    "root": "C:\\Users\\tourg\\OneDrive\\Masaüstü\\SANTIS_PROMPT",
    "manifestPath": "./packs/manifest.json",
    "packCount": 10,
    "totalPrompts": 53,
    "packs": [
      {
        "path": "./packs/pack.ayurveda.js",
        "prompts": 2,
        "ids": 2
      },
      {
        "path": "./packs/pack.brand-look.js",
        "prompts": 3,
        "ids": 3
      },
      {
        "path": "./packs/pack.face-sothys.js",
        "prompts": 4,
        "ids": 4
      },
      {
        "path": "./packs/pack.hamam.js",
        "prompts": 10,
        "ids": 10
      },
      {
        "path": "./packs/pack.kids.js",
        "prompts": 6,
        "ids": 6
      },
      {
        "path": "./packs/pack.kids.premium.js",
        "prompts": 8,
        "ids": 8
      },
      {
        "path": "./packs/pack.recovery.js",
        "prompts": 8,
        "ids": 8
      },
      {
        "path": "./packs/pack.seasonal-detox.js",
        "prompts": 4,
        "ids": 4
      },
      {
        "path": "./packs/pack.signature-family-teen.js",
        "prompts": 4,
        "ids": 4
      },
      {
        "path": "./packs/pack.signature.js",
        "prompts": 4,
        "ids": 4
      }
    ],
    "duplicateIds": [],
    "errors": []
  },
  "safeNoteCoverage": 100,
  "invalidTurkish": []
}
